CHANGELOG.md
README.md
egg_timer/__init__.py
egg_timer/eggtimer.py
egg_timer/py.typed
eggtimer/__init__.py
eggtimer/eggtimer.py
eggtimer/py.typed
egg_timer-1.3.0.dist-info/LICENSE
egg_timer-1.3.0.dist-info/METADATA
egg_timer-1.3.0.dist-info/WHEEL
egg_timer-1.3.0.dist-info/RECORD
