Metadata-Version: 2.1
Name: egg-timer
Version: 1.3.0
Summary: A simpler way to handle timeouts in Python
Home-page: https://github.com/mssalvatore/eggtimer
License: GPLv3
Author: Mike Salvatore
Author-email: mike.s.salvatore@gmail.com
Requires-Python: >=3.7,<4.0
Classifier: Development Status :: 5 - Production/Stable
Classifier: Intended Audience :: Developers
Classifier: License :: OSI Approved :: GNU General Public License v3 (GPLv3)
Classifier: License :: Other/Proprietary License
Classifier: Operating System :: OS Independent
Classifier: Programming Language :: Python :: 3
Classifier: Programming Language :: Python :: 3.7
Classifier: Programming Language :: Python :: 3.8
Classifier: Programming Language :: Python :: 3.9
Classifier: Programming Language :: Python :: 3.10
Classifier: Programming Language :: Python :: 3.11
Classifier: Topic :: Software Development :: Libraries
Classifier: Topic :: Utilities
Project-URL: Repository, https://github.com/mssalvatore/eggtimer
